LICENSE
MANIFEST.in
README.rst
setup.py
pyrasite_gui/__init__.py
pyrasite_gui/gui.py
pyrasite_gui.egg-info/PKG-INFO
pyrasite_gui.egg-info/SOURCES.txt
pyrasite_gui.egg-info/dependency_links.txt
pyrasite_gui.egg-info/entry_points.txt
pyrasite_gui.egg-info/not-zip-safe
pyrasite_gui.egg-info/requires.txt
pyrasite_gui.egg-info/top_level.txt
pyrasite_gui/js/jquery-1.7.1.min.js
pyrasite_gui/js/jquery.sparkline.min.js