Metadata-Version: 1.0
Name: pyrasite-gui
Version: 2.0beta7
Summary: A graphical interface for interacting with running Python processes
Home-page: http://pyrasite.com
Author: Luke Macken
Author-email: lmacken@redhat.com
License: GPLv3
Keywords: debugging injection runtime gtk
Platform: UNKNOWN
Classifier: Development Status :: 4 - Beta
Classifier: Environment :: Console
Classifier: Intended Audience :: Developers
Classifier: Intended Audience :: System Administrators
Classifier: License :: OSI Approved :: GNU General Public License (GPL)
Classifier: Topic :: System :: Monitoring
Classifier: Topic :: Software Development :: Debuggers
Classifier: Programming Language :: Python
Classifier: Programming Language :: Python :: 3
